pysnakepygame/__init__.py
pysnakepygame/__main__.py
pysnakepygame-0.2.1.dist-info/LICENSE
pysnakepygame-0.2.1.dist-info/METADATA
pysnakepygame-0.2.1.dist-info/WHEEL
pysnakepygame-0.2.1.dist-info/entry_points.txt
pysnakepygame-0.2.1.dist-info/top_level.txt
pysnakepygame-0.2.1.dist-info/RECORD
