Metadata-Version: 2.1
Name: pysnakepygame
Version: 0.2.1
Summary: Snake game written with Pygame
Home-page: https://github.com/xXCoolinXx/Snake
Author: Collin Francel
Author-email: collin.t.francel@gmail.com
License: UNKNOWN
Project-URL: Bug Tracker, https://github.com/xXCoolinXx/Snake/issues
Platform: UNKNOWN
Classifier: Programming Language :: Python :: 3
Classifier: License :: OSI Approved :: GNU General Public License v3 or later (GPLv3+)
Classifier: Operating System :: OS Independent
Requires-Python: >=3.6
License-File: LICENSE
Requires-Dist: pygame
